sib_api_v3_sdk/__init__.py
sib_api_v3_sdk/api_client.py
sib_api_v3_sdk/configuration.py
sib_api_v3_sdk/rest.py
sib_api_v3_sdk/api/__init__.py
sib_api_v3_sdk/api/account_api.py
sib_api_v3_sdk/api/attributes_api.py
sib_api_v3_sdk/api/contacts_api.py
sib_api_v3_sdk/api/email_campaigns_api.py
sib_api_v3_sdk/api/folders_api.py
sib_api_v3_sdk/api/lists_api.py
sib_api_v3_sdk/api/process_api.py
sib_api_v3_sdk/api/reseller_api.py
sib_api_v3_sdk/api/senders_api.py
sib_api_v3_sdk/api/sms_campaigns_api.py
sib_api_v3_sdk/api/smtp_api.py
sib_api_v3_sdk/api/transactional_sms_api.py
sib_api_v3_sdk/api/webhooks_api.py
sib_api_v3_sdk/models/__init__.py
sib_api_v3_sdk/models/add_child_domain.py
sib_api_v3_sdk/models/add_contact_to_list.py
sib_api_v3_sdk/models/add_credits.py
sib_api_v3_sdk/models/create_attribute.py
sib_api_v3_sdk/models/create_attribute_enumeration.py
sib_api_v3_sdk/models/create_child.py
sib_api_v3_sdk/models/create_contact.py
sib_api_v3_sdk/models/create_email_campaign.py
sib_api_v3_sdk/models/create_email_campaign_recipients.py
sib_api_v3_sdk/models/create_email_campaign_sender.py
sib_api_v3_sdk/models/create_list.py
sib_api_v3_sdk/models/create_model.py
sib_api_v3_sdk/models/create_reseller.py
sib_api_v3_sdk/models/create_sender.py
sib_api_v3_sdk/models/create_sender_ips.py
sib_api_v3_sdk/models/create_sender_model.py
sib_api_v3_sdk/models/create_sms_campaign.py
sib_api_v3_sdk/models/create_sms_campaign_recipients.py
sib_api_v3_sdk/models/create_smtp_email.py
sib_api_v3_sdk/models/create_smtp_template.py
sib_api_v3_sdk/models/create_smtp_template_sender.py
sib_api_v3_sdk/models/create_update_contact_model.py
sib_api_v3_sdk/models/create_update_folder.py
sib_api_v3_sdk/models/create_webhook.py
sib_api_v3_sdk/models/created_process_id.py
sib_api_v3_sdk/models/delete_hardbounces.py
sib_api_v3_sdk/models/email_export_recipients.py
sib_api_v3_sdk/models/error_model.py
sib_api_v3_sdk/models/get_account.py
sib_api_v3_sdk/models/get_account_marketing_automation.py
sib_api_v3_sdk-6.0.3.dist-info/LICENSE.md
sib_api_v3_sdk-6.0.3.dist-info/METADATA
sib_api_v3_sdk-6.0.3.dist-info/WHEEL
sib_api_v3_sdk-6.0.3.dist-info/top_level.txt
sib_api_v3_sdk-6.0.3.dist-info/RECORD
