Metadata-Version: 2.1
Name: sib-api-v3-sdk
Version: 6.0.3
Summary: SendinBlue API
Home-page: UNKNOWN
Author: UNKNOWN
Author-email: contact@sendinblue.com
License: UNKNOWN
Keywords: Swagger,SendinBlue API
Platform: UNKNOWN
Requires-Dist: urllib3 (>=1.15)
Requires-Dist: six (>=1.10)
Requires-Dist: certifi
Requires-Dist: python-dateutil
